RankBasedMonteCarlo/.DS_Store
RankBasedMonteCarlo/Methods.py
RankBasedMonteCarlo/__init__.py
rankbasedmontecarlo-0.1.4.dist-info/METADATA
rankbasedmontecarlo-0.1.4.dist-info/WHEEL
rankbasedmontecarlo-0.1.4.dist-info/licenses/LICENSE
rankbasedmontecarlo-0.1.4.dist-info/RECORD
