Metadata-Version: 2.1
Name: RankBasedMonteCarlo
Version: 0.1.4
Summary: A set of Monte Carlo based tools to create test statistics for four non-parametric rank-based tests: Mann-Whitney (MW), Kruskal-Wallis (KW), Kolmogorov-Smirnov (KS) and Kuiper (K).
Project-URL: Homepage, https://github.com/tazzben/RankBasedMonteCarlo
Project-URL: Bug Tracker, https://github.com/tazzben/RankBasedMonteCarlo/issues
Author-email: Ben Smith <bosmith@unomaha.edu>
Maintainer-email: Ben Smith <bosmith@unomaha.edu>
License-Expression: MIT
License-File: LICENSE
Keywords: Monte Carlo,Rank based,Statistics
Classifier: Development Status :: 5 - Production/Stable
Classifier: Intended Audience :: Science/Research
Classifier: License :: OSI Approved :: MIT License
Classifier: Programming Language :: Python :: 3.8
Classifier: Programming Language :: Python :: 3.9
Classifier: Programming Language :: Python :: 3.10
Classifier: Programming Language :: Python :: 3.11
Requires-Python: >=3.8
Requires-Dist: numpy>=1.21.0
Requires-Dist: pandas>=1.3.0
Requires-Dist: tqdm>=4.26.0
